shprits/__init__.py
shprits/decorators.py
shprits/core/__init__.py
shprits/core/container.py
shprits/core/entities.py
shprits/core/exceptions.py
shprits-0.1.0.dist-info/licenses/LICENSE
shprits-0.1.0.dist-info/METADATA
shprits-0.1.0.dist-info/WHEEL
shprits-0.1.0.dist-info/top_level.txt
shprits-0.1.0.dist-info/RECORD
