Metadata-Version: 2.4
Name: shprits
Version: 0.1.0
Summary: A Dependency Injection framework for Python.
Author-email: Arseny Seliverstov <asel1x@icloud.com>
License:                                  Apache License
Project-URL: Homepage, https://github.com/aSel1x/shprits
Requires-Python: >=3.11
License-File: LICENSE
Provides-Extra: test
Requires-Dist: pytest; extra == "test"
Requires-Dist: pytest-asyncio; extra == "test"
Provides-Extra: dev
Requires-Dist: ruff; extra == "dev"
Requires-Dist: pip-audit; extra == "dev"
Provides-Extra: examples
Requires-Dist: uvicorn; extra == "examples"
Requires-Dist: litestar; extra == "examples"
Requires-Dist: flask; extra == "examples"
Dynamic: license-file
